phasenet/__init__.py
phasenet/data_reader.py
phasenet/detect_peaks.py
phasenet/model.py
phasenet/predict.py
phasenet/train.py
phasenet/util.py
PhaseNet-0.1.0.dist-info/LICENSE
PhaseNet-0.1.0.dist-info/METADATA
PhaseNet-0.1.0.dist-info/WHEEL
PhaseNet-0.1.0.dist-info/top_level.txt
PhaseNet-0.1.0.dist-info/RECORD
