Metadata-Version: 2.1
Name: PhaseNet
Version: 0.1.0
Summary: PhaseNet
Home-page: UNKNOWN
Author: Weiqiang Zhu
Author-email: wayne.weiqiang@gmail.com
License: GPL-3.0
Platform: UNKNOWN
Classifier: License :: OSI Approved :: BSD License
Classifier: Intended Audience :: Developers
Classifier: Intended Audience :: Science/Research
Classifier: Operating System :: OS Independent
Classifier: Programming Language :: Python
Classifier: Programming Language :: Python :: 3
Classifier: Topic :: Software Development :: Libraries
Classifier: Topic :: Software Development :: Libraries :: Python Modules
Requires-Dist: tensorflow (==2.3)
Requires-Dist: matplotlib
Requires-Dist: pandas
Requires-Dist: tqdm
Requires-Dist: scipy
Requires-Dist: obspy (==1.2.2)
Provides-Extra: test
Requires-Dist: pytest ; extra == 'test'
